pytoontown/__init__.py
pytoontown/corporateclash.py
pytoontown/toontownrewritten.py
pytoontown-0.0.6.dist-info/LICENSE
pytoontown-0.0.6.dist-info/METADATA
pytoontown-0.0.6.dist-info/WHEEL
pytoontown-0.0.6.dist-info/top_level.txt
pytoontown-0.0.6.dist-info/RECORD
