Metadata-Version: 2.1
Name: pytoontown
Version: 0.0.6
Summary: A Python API wrapper for the Toontown Rewritten and Corporate Clash APIs
Home-page: https://github.com/Koalacards/pytoontown
Author: Koalacards
Author-email: deanglhayd@gmail.com
License: UNKNOWN
Project-URL: Documentation, https://github.com/Koalacards/pytoontown/blob/main/DOCS.md
Project-URL: Bug Tracker, https://github.com/Koalacards/pytoontown/issues
Platform: UNKNOWN
Classifier: Programming Language :: Python :: 3
Classifier: License :: OSI Approved :: MIT License
Classifier: Operating System :: OS Independent
Requires-Python: >=3.6
License-File: LICENSE
